PyDbTool/__init__.py
PyDbTool-3.0.0.dist-info/LICENSE
PyDbTool-3.0.0.dist-info/METADATA
PyDbTool-3.0.0.dist-info/WHEEL
PyDbTool-3.0.0.dist-info/top_level.txt
PyDbTool-3.0.0.dist-info/RECORD
