Metadata-Version: 2.1
Name: PyDbTool
Version: 3.0.0
Summary: Python all in one data-driver
Home-page: https://pypi.org/project/PyDbTool/
Author: Prabir Ghosh
Author-email: mymail.prabir@gmail.com
License: MIT
Platform: UNKNOWN
Requires-Dist: pandas
Requires-Dist: psycopg2
Requires-Dist: cassandra-driver
Requires-Dist: pymongo
